.dockerignore
.gitignore
.gitmodules
.readthedocs.yaml
CHANGELOG.md
CMakeLists.txt
LICENSE.md
Makefile
README.md
mkdocs.yml
poetry.lock
poetry.toml
pyproject.toml
setup.py
.github/dependabot.yml
.github/ISSUE_TEMPLATE/bug_report.md
.github/ISSUE_TEMPLATE/feature_request.md
.github/workflows/build-and-release.yaml
.github/workflows/build-docker.yaml
.github/workflows/publish-to-test.yaml
.github/workflows/publish.yaml
.github/workflows/test-pypi.yaml
.github/workflows/test.yaml
docker/README.md
docker/cuda_simple/Dockerfile
docker/open_llama/Dockerfile
docker/open_llama/build.sh
docker/open_llama/hug_model.py
docker/open_llama/start.sh
docker/open_llama/start_server.sh
docker/openblas_simple/Dockerfile
docker/simple/Dockerfile
docker/simple/run.sh
docs/api-reference.md
docs/index.md
docs/requirements.txt
docs/install/macos.md
examples/high_level_api/fastapi_server.py
examples/high_level_api/high_level_api_embedding.py
examples/high_level_api/high_level_api_inference.py
examples/high_level_api/high_level_api_streaming.py
examples/high_level_api/langchain_custom_llm.py
examples/low_level_api/Chat.py
examples/low_level_api/Miku.py
examples/low_level_api/ReasonAct.py
examples/low_level_api/common.py
examples/low_level_api/low_level_api_chat_cpp.py
examples/low_level_api/low_level_api_llama_cpp.py
examples/low_level_api/quantize.py
examples/low_level_api/util.py
examples/notebooks/Clients.ipynb
examples/notebooks/Guidance.ipynb
examples/notebooks/PerformanceTuning.ipynb
llama_cpp/__init__.py
llama_cpp/llama.py
llama_cpp/llama_cpp.py
llama_cpp/llama_grammar.py
llama_cpp/llama_types.py
llama_cpp/py.typed
llama_cpp/utils.py
llama_cpp/version.py
llama_cpp/server/__init__.py
llama_cpp/server/__main__.py
llama_cpp/server/app.py
llama_cpp_python.egg-info/PKG-INFO
llama_cpp_python.egg-info/SOURCES.txt
llama_cpp_python.egg-info/dependency_links.txt
llama_cpp_python.egg-info/requires.txt
llama_cpp_python.egg-info/top_level.txt
tests/test_llama.py
vendor/llama.cpp/.clang-tidy
vendor/llama.cpp/.dockerignore
vendor/llama.cpp/.ecrc
vendor/llama.cpp/.editorconfig
vendor/llama.cpp/.flake8
vendor/llama.cpp/.gitignore
vendor/llama.cpp/.pre-commit-config.yaml
