Metadata-Version: 2.1
Name: llama-cpp-python
Version: 0.1.85
Summary: A Python wrapper for llama.cpp
Author: Andrei Betlen
Author-email: abetlen@gmail.com
License: MIT
Classifier: Programming Language :: Python :: 3
Classifier: Programming Language :: Python :: 3.7
Classifier: Programming Language :: Python :: 3.8
Classifier: Programming Language :: Python :: 3.9
Classifier: Programming Language :: Python :: 3.10
Classifier: Programming Language :: Python :: 3.11
Requires-Python: >=3.7
License-File: LICENSE.md
Requires-Dist: typing-extensions>=4.5.0
Requires-Dist: numpy>=1.20.0
Requires-Dist: diskcache>=5.6.1
Provides-Extra: server
Requires-Dist: uvicorn>=0.22.0; extra == "server"
Requires-Dist: fastapi>=0.100.0; extra == "server"
Requires-Dist: pydantic-settings>=2.0.1; extra == "server"
Requires-Dist: sse-starlette>=1.6.1; extra == "server"
